markdown_gettext/__init__.py
markdown_gettext/cli.py
markdown_gettext/domain_extraction.py
markdown_gettext/domain_generation.py
markdown_gettext-0.2.1.dist-info/entry_points.txt
markdown_gettext-0.2.1.dist-info/LICENSES/CC-BY-SA-4.0.txt
markdown_gettext-0.2.1.dist-info/LICENSES/LGPL-2.1-or-later.txt
markdown_gettext-0.2.1.dist-info/LICENSES/CC0-1.0.txt
markdown_gettext-0.2.1.dist-info/WHEEL
markdown_gettext-0.2.1.dist-info/METADATA
markdown_gettext-0.2.1.dist-info/RECORD
