Metadata-Version: 2.1
Name: markdown-gettext
Version: 0.2.1
Summary: Markdown i18n with gettext
Home-page: https://github.com/phunh/markdown-gettext
License: LGPL-2.1-or-later
Author: Phu Hung Nguyen
Author-email: phuhnguyen@outlook.com
Requires-Python: >=3.8,<4.0
Classifier: Development Status :: 3 - Alpha
Classifier: Intended Audience :: Developers
Classifier: License :: OSI Approved
Classifier: Programming Language :: Python
Classifier: Programming Language :: Python :: 3
Classifier: Programming Language :: Python :: 3.10
Classifier: Programming Language :: Python :: 3.8
Classifier: Programming Language :: Python :: 3.9
Classifier: Topic :: Software Development :: Internationalization
Requires-Dist: PyYAML (>=5.3,<6.0); python_version >= "3.8" and python_version < "3.10"
Requires-Dist: PyYAML (>=6.0.1,<7.0.0); python_version >= "3.10"
Requires-Dist: mdit-py-i18n (>=0.2.1,<0.3.0)
Requires-Dist: polib (>=1.2.0,<2.0.0)
Project-URL: Repository, https://github.com/phunh/markdown-gettext
